src/__init__.py
src/app.py
src/db/__init__.py
src/db/database_instance.py
src/runner/__init__.py
src/runner/update_runner.py
src/settings/__init__.py
src/settings/settings.py
tests/__init__.py
tests/runner/__init__.py
tests/runner/update_runner_unit_test.py
config_cobra-0.1.6.dist-info/LICENSE
config_cobra-0.1.6.dist-info/METADATA
config_cobra-0.1.6.dist-info/WHEEL
config_cobra-0.1.6.dist-info/entry_points.txt
config_cobra-0.1.6.dist-info/top_level.txt
config_cobra-0.1.6.dist-info/RECORD
