Metadata-Version: 2.1
Name: config-cobra
Version: 0.1.6
Summary: A simple yaml to database updater
Home-page: https://github.com/JTSG1/configCobra
License: MIT
Platform: UNKNOWN
License-File: LICENSE
Requires-Dist: PyYAML ==6.0.1
Requires-Dist: SQLAlchemy ==2.0.30
Requires-Dist: exceptiongroup ==1.2.1
Requires-Dist: greenlet ==3.0.3
Requires-Dist: iniconfig ==2.0.0
Requires-Dist: packaging ==24.0
Requires-Dist: pluggy ==1.5.0
Requires-Dist: psycopg2-binary ==2.9.9
Requires-Dist: pytest ==8.2.0
Requires-Dist: python-dotenv ==1.0.1
Requires-Dist: tomli ==2.0.1
Requires-Dist: typing-extensions ==4.11.0
